solidipes/__init__.py
solidipes/__main__.py
solidipes/downloaders/__init__.py
solidipes/downloaders/downloader.py
solidipes/loaders/__init__.py
solidipes/loaders/binary.py
solidipes/loaders/cached_metadata.py
solidipes/loaders/data_container.py
solidipes/loaders/file.py
solidipes/loaders/file_sequence.py
solidipes/loaders/group.py
solidipes/loaders/mime_types.py
solidipes/loaders/rocrate_metadata.py
solidipes/loaders/sequence.py
solidipes/loaders/symlink.py
solidipes/loaders/virtual_file.py
solidipes/mounters/__init__.py
solidipes/mounters/cloud.py
solidipes/plugins/discovery.py
solidipes/plugins/lazy_lists.py
solidipes/plugins/management.py
solidipes/reports/__init__.py
solidipes/reports/curation.py
solidipes/reports/report.py
solidipes/scanners/__init__.py
solidipes/scanners/scanner.py
solidipes/scanners/scanner_dtool.py
solidipes/scanners/scanner_local.py
solidipes/scripts/__init__.py
solidipes/scripts/download.py
solidipes/scripts/generate_report.py
solidipes/scripts/init.py
solidipes/scripts/install_completion.py
solidipes/scripts/main.py
solidipes/scripts/mount.py
solidipes/scripts/quick_view.py
solidipes/scripts/shell.py
solidipes/scripts/shell_environment.py
solidipes/scripts/unmount.py
solidipes/scripts/upload.py
solidipes/uploaders/__init__.py
solidipes/uploaders/uploader.py
solidipes/utils/__init__.py
solidipes/utils/config.py
solidipes/utils/git_infos.py
solidipes/utils/languages-iso-639-2.csv
solidipes/utils/licenses.csv
solidipes/utils/metadata.py
solidipes/utils/parsable.py
solidipes/utils/progress.py
solidipes/utils/solidipes_logging.py
solidipes/utils/utils.py
solidipes/validators/__init__.py
solidipes/validators/curation.py
solidipes/validators/global_validation.py
solidipes/validators/validator.py
solidipes/viewers/__init__.py
solidipes/viewers/backends.py
solidipes/viewers/binary.py
solidipes/viewers/symlink.py
solidipes/viewers/viewer.py
solidipes-1.4.2.dist-info/licenses/AUTHORS
solidipes-1.4.2.dist-info/licenses/LICENSE
solidipes-1.4.2.dist-info/METADATA
solidipes-1.4.2.dist-info/WHEEL
solidipes-1.4.2.dist-info/entry_points.txt
solidipes-1.4.2.dist-info/top_level.txt
solidipes-1.4.2.dist-info/RECORD
